django_lti_provider_auth-0.2.0.dist-info/licenses/LICENSE
lti_provider/__init__.py
lti_provider/admin.py
lti_provider/apps.py
lti_provider/backends.py
lti_provider/field_validators.py
lti_provider/models.py
lti_provider/tests.py
lti_provider/urls.py
lti_provider/utils.py
lti_provider/validators.py
lti_provider/views.py
lti_provider/migrations/0001_initial.py
lti_provider/migrations/0002_auto_20170914_1603.py
lti_provider/migrations/__init__.py
django_lti_provider_auth-0.2.0.dist-info/METADATA
django_lti_provider_auth-0.2.0.dist-info/WHEEL
django_lti_provider_auth-0.2.0.dist-info/top_level.txt
django_lti_provider_auth-0.2.0.dist-info/RECORD
